odoo/addons/repair_stock/README.rst
odoo/addons/repair_stock/__init__.py
odoo/addons/repair_stock/__manifest__.py
odoo/addons/repair_stock/i18n/it.po
odoo/addons/repair_stock/i18n/repair_stock.pot
odoo/addons/repair_stock/models/__init__.py
odoo/addons/repair_stock/models/repair.py
odoo/addons/repair_stock/readme/CONTRIBUTORS.rst
odoo/addons/repair_stock/readme/DESCRIPTION.rst
odoo/addons/repair_stock/static/description/icon.png
odoo/addons/repair_stock/static/description/index.html
odoo/addons/repair_stock/tests/__init__.py
odoo/addons/repair_stock/tests/test_stock_repair_order.py
odoo/addons/repair_stock/views/repair_order_view.xml
odoo14_addon_repair_stock-14.0.1.0.1.dev4.dist-info/METADATA
odoo14_addon_repair_stock-14.0.1.0.1.dev4.dist-info/WHEEL
odoo14_addon_repair_stock-14.0.1.0.1.dev4.dist-info/top_level.txt
odoo14_addon_repair_stock-14.0.1.0.1.dev4.dist-info/RECORD
